[
{"SkillCount":1,"SkillPoints":[1,2,2],"TroopCount":1,"CostMedal":0,"CostGold":0,"CostItemId":0,"CostItemCount":0,"CostRates":[1.0,1.5,2.0],"Icon":null,"Id":1,"Name":"队尾长1","Disabled":false},
{"SkillCount":1,"SkillPoints":[2,3,4],"TroopCount":1,"CostMedal":0,"CostGold":250,"CostItemId":0,"CostItemCount":0,"CostRates":[1.0,1.5,2.0],"Icon":null,"Id":2,"Name":"队尾长2","Disabled":false},
{"SkillCount":1,"SkillPoints":[3,5,7],"TroopCount":1,"CostMedal":0,"CostGold":250,"CostItemId":0,"CostItemCount":0,"CostRates":[1.0,1.5,2.0],"Icon":null,"Id":3,"Name":"队尾长3","Disabled":false},
{"SkillCount":2,"SkillPoints":[4,6,8],"TroopCount":1,"CostMedal":0,"CostGold":750,"CostItemId":0,"CostItemCount":0,"CostRates":[1.0,1.5,2.0],"Icon":null,"Id":4,"Name":"五夫长1","Disabled":false},
{"SkillCount":2,"SkillPoints":[5,8,10],"TroopCount":1,"CostMedal":0,"CostGold":1000,"CostItemId":0,"CostItemCount":0,"CostRates":[1.0,1.5,2.0],"Icon":null,"Id":5,"Name":"五夫长2","Disabled":false},
{"SkillCount":2,"SkillPoints":[7,11,14],"TroopCount":1,"CostMedal":0,"CostGold":1000,"CostItemId":0,"CostItemCount":0,"CostRates":[1.0,1.5,2.0],"Icon":null,"Id":6,"Name":"五夫长3","Disabled":false},
{"SkillCount":2,"SkillPoints":[8,12,15],"TroopCount":1,"CostMedal":0,"CostGold":1500,"CostItemId":12,"CostItemCount":2,"CostRates":[1.0,1.5,2.0],"Icon":null,"Id":7,"Name":"十夫长1","Disabled":false},
{"SkillCount":2,"SkillPoints":[9,13,17],"TroopCount":1,"CostMedal":0,"CostGold":1750,"CostItemId":0,"CostItemCount":0,"CostRates":[1.0,1.5,2.0],"Icon":null,"Id":8,"Name":"十夫长2","Disabled":false},
{"SkillCount":2,"SkillPoints":[10,16,21],"TroopCount":1,"CostMedal":0,"CostGold":1750,"CostItemId":0,"CostItemCount":0,"CostRates":[1.0,1.5,2.0],"Icon":null,"Id":9,"Name":"十夫长3","Disabled":false},
{"SkillCount":3,"SkillPoints":[11,17,22],"TroopCount":1,"CostMedal":0,"CostGold":2250,"CostItemId":12,"CostItemCount":4,"CostRates":[1.0,1.5,2.0],"Icon":null,"Id":10,"Name":"百夫长1","Disabled":false},
{"SkillCount":3,"SkillPoints":[12,18,24],"TroopCount":1,"CostMedal":0,"CostGold":2500,"CostItemId":0,"CostItemCount":0,"CostRates":[1.0,1.5,2.0],"Icon":null,"Id":11,"Name":"百夫长2","Disabled":false},
{"SkillCount":3,"SkillPoints":[14,21,28],"TroopCount":1,"CostMedal":0,"CostGold":2500,"CostItemId":0,"CostItemCount":0,"CostRates":[1.0,1.5,2.0],"Icon":null,"Id":12,"Name":"百夫长3","Disabled":false},
{"SkillCount":3,"SkillPoints":[15,22,29],"TroopCount":2,"CostMedal":0,"CostGold":3000,"CostItemId":12,"CostItemCount":6,"CostRates":[1.0,1.5,2.0],"Icon":null,"Id":13,"Name":"骑士队长1","Disabled":false},
{"SkillCount":3,"SkillPoints":[16,23,31],"TroopCount":2,"CostMedal":0,"CostGold":3250,"CostItemId":0,"CostItemCount":0,"CostRates":[1.0,1.5,2.0],"Icon":null,"Id":14,"Name":"骑士队长2","Disabled":false},
{"SkillCount":3,"SkillPoints":[17,26,35],"TroopCount":2,"CostMedal":0,"CostGold":3250,"CostItemId":0,"CostItemCount":0,"CostRates":[1.0,1.5,2.0],"Icon":null,"Id":15,"Name":"骑士队长3","Disabled":false},
{"SkillCount":4,"SkillPoints":[18,27,36],"TroopCount":2,"CostMedal":0,"CostGold":3750,"CostItemId":12,"CostItemCount":8,"CostRates":[1.0,1.5,2.0],"Icon":null,"Id":16,"Name":"统领1","Disabled":false},
{"SkillCount":4,"SkillPoints":[19,29,38],"TroopCount":2,"CostMedal":0,"CostGold":4000,"CostItemId":0,"CostItemCount":0,"CostRates":[1.0,1.5,2.0],"Icon":null,"Id":17,"Name":"统领2","Disabled":false},
{"SkillCount":4,"SkillPoints":[21,32,42],"TroopCount":2,"CostMedal":0,"CostGold":4000,"CostItemId":0,"CostItemCount":0,"CostRates":[1.0,1.5,2.0],"Icon":null,"Id":18,"Name":"统领3","Disabled":false},
{"SkillCount":4,"SkillPoints":[22,33,43],"TroopCount":2,"CostMedal":0,"CostGold":4500,"CostItemId":12,"CostItemCount":10,"CostRates":[1.0,1.5,2.0],"Icon":null,"Id":19,"Name":"分队指挥官1","Disabled":false},
{"SkillCount":4,"SkillPoints":[23,34,45],"TroopCount":2,"CostMedal":0,"CostGold":4750,"CostItemId":0,"CostItemCount":0,"CostRates":[1.0,1.5,2.0],"Icon":null,"Id":20,"Name":"分队指挥官2","Disabled":false},
{"SkillCount":4,"SkillPoints":[24,37,49],"TroopCount":2,"CostMedal":0,"CostGold":4750,"CostItemId":0,"CostItemCount":0,"CostRates":[1.0,1.5,2.0],"Icon":null,"Id":21,"Name":"分队指挥官3","Disabled":false},
{"SkillCount":5,"SkillPoints":[25,38,50],"TroopCount":2,"CostMedal":0,"CostGold":5250,"CostItemId":12,"CostItemCount":12,"CostRates":[1.0,1.5,2.0],"Icon":null,"Id":22,"Name":"军阵指挥官1","Disabled":false},
{"SkillCount":5,"SkillPoints":[26,39,52],"TroopCount":2,"CostMedal":0,"CostGold":5500,"CostItemId":0,"CostItemCount":0,"CostRates":[1.0,1.5,2.0],"Icon":null,"Id":23,"Name":"军阵指挥官2","Disabled":false},
{"SkillCount":5,"SkillPoints":[28,42,56],"TroopCount":2,"CostMedal":0,"CostGold":5500,"CostItemId":0,"CostItemCount":0,"CostRates":[1.0,1.5,2.0],"Icon":null,"Id":24,"Name":"军阵指挥官3","Disabled":false},
{"SkillCount":5,"SkillPoints":[29,43,57],"TroopCount":3,"CostMedal":0,"CostGold":6000,"CostItemId":12,"CostItemCount":14,"CostRates":[1.0,1.5,2.0],"Icon":null,"Id":25,"Name":"副将1","Disabled":false},
{"SkillCount":5,"SkillPoints":[30,44,59],"TroopCount":3,"CostMedal":0,"CostGold":6250,"CostItemId":0,"CostItemCount":0,"CostRates":[1.0,1.5,2.0],"Icon":null,"Id":26,"Name":"副将2","Disabled":false},
{"SkillCount":5,"SkillPoints":[31,47,63],"TroopCount":3,"CostMedal":0,"CostGold":6250,"CostItemId":0,"CostItemCount":0,"CostRates":[1.0,1.5,2.0],"Icon":null,"Id":27,"Name":"副将3","Disabled":false},
{"SkillCount":5,"SkillPoints":[32,49,65],"TroopCount":3,"CostMedal":0,"CostGold":6750,"CostItemId":12,"CostItemCount":16,"CostRates":[1.0,1.5,2.0],"Icon":null,"Id":28,"Name":"将军1","Disabled":false},
{"SkillCount":5,"SkillPoints":[34,51,68],"TroopCount":3,"CostMedal":0,"CostGold":7000,"CostItemId":0,"CostItemCount":0,"CostRates":[1.0,1.5,2.0],"Icon":null,"Id":29,"Name":"将军2","Disabled":false},
{"SkillCount":5,"SkillPoints":[36,54,72],"TroopCount":3,"CostMedal":0,"CostGold":7250,"CostItemId":0,"CostItemCount":0,"CostRates":[1.0,1.5,2.0],"Icon":null,"Id":30,"Name":"将军3","Disabled":false}
]